pyfreedts/__init__.py
pyfreedts/_bin/CNV
pyfreedts/_bin/DTS
pyfreedts/_bin/GEN
pyfreedts/_cpp/compile.sh
pyfreedts/_cpp/dts_convert/Convert.cpp
pyfreedts/_cpp/dts_convert/Convert.h
pyfreedts/_cpp/dts_convert/Convert.o
pyfreedts/_cpp/dts_convert/Def.h
pyfreedts/_cpp/dts_convert/MeshBluePrint.h
pyfreedts/_cpp/dts_convert/Nfunction.cpp
pyfreedts/_cpp/dts_convert/Nfunction.h
pyfreedts/_cpp/dts_convert/Nfunction.o
pyfreedts/_cpp/dts_convert/QFile.cpp
pyfreedts/_cpp/dts_convert/QFile.h
pyfreedts/_cpp/dts_convert/QFile.o
pyfreedts/_cpp/dts_convert/TSIFile.cpp
pyfreedts/_cpp/dts_convert/TSIFile.h
pyfreedts/_cpp/dts_convert/TSIFile.o
pyfreedts/_cpp/dts_convert/VMDOutput.cpp
pyfreedts/_cpp/dts_convert/VMDOutput.h
pyfreedts/_cpp/dts_convert/VMDOutput.o
pyfreedts/_cpp/dts_convert/Vec3D.cpp
pyfreedts/_cpp/dts_convert/Vec3D.h
pyfreedts/_cpp/dts_convert/Vec3D.o
pyfreedts/_cpp/dts_convert/WritevtuFiles.cpp
pyfreedts/_cpp/dts_convert/WritevtuFiles.h
pyfreedts/_cpp/dts_convert/WritevtuFiles.o
pyfreedts/_cpp/dts_convert/main.cpp
pyfreedts/_cpp/dts_convert/main.o
pyfreedts/_cpp/dts_generate/DMC.cpp
pyfreedts/_cpp/dts_generate/DMC.o
pyfreedts/_cpp/dts_generate/Def.h
pyfreedts/_cpp/dts_generate/Generate.cpp
pyfreedts/_cpp/dts_generate/Generate.h
pyfreedts/_cpp/dts_generate/Generate.o
pyfreedts/_cpp/dts_generate/Nfunction.cpp
pyfreedts/_cpp/dts_generate/Nfunction.h
pyfreedts/_cpp/dts_generate/Nfunction.o
pyfreedts/_cpp/dts_generate/Vec3D.cpp
pyfreedts/_cpp/dts_generate/Vec3D.h
pyfreedts/_cpp/dts_generate/Vec3D.o
pyfreedts/_cpp/dts_src/AbstractAlexanderMove.h
pyfreedts/_cpp/dts_src/AbstractApplyConstraintBetweenGroups.h
pyfreedts/_cpp/dts_src/AbstractBinaryTrajectory.h
pyfreedts/_cpp/dts_src/AbstractBondedPotentialBetweenVertices.h
pyfreedts/_cpp/dts_src/AbstractBoundary.h
pyfreedts/_cpp/dts_src/AbstractCurvature.h
pyfreedts/_cpp/dts_src/AbstractDynamicBox.h
pyfreedts/_cpp/dts_src/AbstractDynamicTopology.h
pyfreedts/_cpp/dts_src/AbstractEnergy.h
pyfreedts-2.1.0.post1.dist-info/LICENSE.md
pyfreedts-2.1.0.post1.dist-info/METADATA
pyfreedts-2.1.0.post1.dist-info/WHEEL
pyfreedts-2.1.0.post1.dist-info/entry_points.txt
pyfreedts-2.1.0.post1.dist-info/RECORD
