Metadata-Version: 2.3
Name: pyfreedts
Version: 2.1.0.post1
Summary: Python wrapper for the FreeDTS C++ project
License: CC-BY-NC-ND-4.0
Author: Valentin Maurer
Author-email: valentin.maurer@embl-hamburg.de
Requires-Python: >=3.8,<4.0
Classifier: License :: Other/Proprietary License
Classifier: Programming Language :: Python :: 3
Classifier: Programming Language :: Python :: 3.8
Classifier: Programming Language :: Python :: 3.9
Classifier: Programming Language :: Python :: 3.10
Classifier: Programming Language :: Python :: 3.11
Classifier: Programming Language :: Python :: 3.12
Classifier: Programming Language :: Python :: 3.13
